mat_rajagopal/__init__.py
mat_rajagopal/mat_raja.py
mat_rajagopal-0.0.5.dist-info/LICENSE.txt
mat_rajagopal-0.0.5.dist-info/METADATA
mat_rajagopal-0.0.5.dist-info/WHEEL
mat_rajagopal-0.0.5.dist-info/top_level.txt
mat_rajagopal-0.0.5.dist-info/RECORD
