Metadata-Version: 2.1
Name: mat-rajagopal
Version: 0.0.5
Summary: it has a wide operation of matrix like addition , subtraction , multiplication , division.we can use it for,a matrix satisfy the properties and determinant is also available.
Author-email: Rajagopal <mugundhanrajagopal005@gmail.com>
Classifier: Programming Language :: Python :: 3
Classifier: License :: OSI Approved :: MIT License
Classifier: Operating System :: OS Independent
Requires-Python: >=3.7
License-File: LICENSE.txt
